the_crawler/__init__.py
the_crawler/log_handler.py
the_crawler/util.py
the_crawler-0.5.0.dist-info/METADATA
the_crawler-0.5.0.dist-info/WHEEL
the_crawler-0.5.0.dist-info/entry_points.txt
the_crawler-0.5.0.dist-info/RECORD
