Metadata-Version: 2.1
Name: the-crawler
Version: 0.5.0
Summary: For crawling web file explorers for content
Home-page: https://woodforsheep.trade/the-crawler
Author: deeoh
Author-email: deeoh@woodforsheep.trade
Requires-Python: >=3.10,<4.0
Classifier: Programming Language :: Python :: 3
Classifier: Programming Language :: Python :: 3.10
Classifier: Programming Language :: Python :: 3.11
Requires-Dist: beautifulsoup4 (>=4.12.2,<5.0.0)
Requires-Dist: requests (>=2.31.0,<3.0.0)
Requires-Dist: tqdm (>=4.66.1,<5.0.0)
Project-URL: Documentation, https://gitlab.com/woodforsheep/the-crawler
Project-URL: Repository, https://gitlab.com/woodforsheep/the-crawler
